{
	"parent": "minecraft:recipes/root",
	"rewards": {
		"recipes": [
			"vanillaextension:yellow_terracotta_stairs"
		]
	},
	"criteria": {
		"has_block": {
			"trigger": "minecraft:inventory_changed",
			"conditions": {
				"items": [
					{
						"item": "minecraft:yellow_terracotta"
					}
				]
			}
		},
		"has_the_recipe": {
			"trigger": "minecraft:recipe_unlocked",
			"conditions": {
				"recipe": "vanillaextension:yellow_terracotta_stairs"
			}
		}
	},
	"requirements": [
		[
			"has_block",
			"has_the_recipe"
		]
	]
}